makeprop/__init__.py
makeprop/core/__init__.py
makeprop/tests/__init__.py
makeprop/tests/test_0.py
makeprop-1.0.1.dist-info/LICENSE.txt
makeprop-1.0.1.dist-info/METADATA
makeprop-1.0.1.dist-info/WHEEL
makeprop-1.0.1.dist-info/top_level.txt
makeprop-1.0.1.dist-info/RECORD
