Metadata-Version: 2.1
Name: makeprop
Version: 1.0.1
Summary: This projects allows you to easily create a simple property.
Author-email: Johannes <johannes.programming@gmail.com>
License: The MIT License (MIT)
Project-URL: Download, https://pypi.org/project/makeprop/#files
Project-URL: Index, https://pypi.org/project/makeprop/
Project-URL: Source, https://github.com/johannes-programming/makeprop/
Project-URL: Website, https://makeprop.johannes-programming.online/
Platform: UNKNOWN
Classifier: Development Status :: 5 - Production/Stable
Classifier: License :: OSI Approved :: MIT License
Classifier: Natural Language :: English
Classifier: Operating System :: OS Independent
Classifier: Programming Language :: Python
Classifier: Programming Language :: Python :: 3
Classifier: Programming Language :: Python :: 3 :: Only
Classifier: Typing :: Typed
Requires-Python: >=3.11
License-File: LICENSE.txt
Requires-Dist: overloadable<2,>=1.0.9
